ec2ninja/__init__.py
ec2ninja/manager.py
ec2ninja-1.1.dist-info/METADATA
ec2ninja-1.1.dist-info/WHEEL
ec2ninja-1.1.dist-info/top_level.txt
ec2ninja-1.1.dist-info/RECORD
